pyWake/__init__.py
pyWake/crc.py
pyWake/rx_frame.py
pyWake/wake.py
wakeProtocol-0.0.1.dist-info/LICENSE
wakeProtocol-0.0.1.dist-info/METADATA
wakeProtocol-0.0.1.dist-info/WHEEL
wakeProtocol-0.0.1.dist-info/top_level.txt
wakeProtocol-0.0.1.dist-info/RECORD
